{
  "name": "decolle_conv_snn_cifar10_t6",
  "trainer": "decolle",
  "model": "conv_snn",
  "dataset": "cifar10",
  "test_accuracy": 0.0851,
  "train_loss": 0.8002390389442444,
  "elapsed_s": 295.6344954967499,
  "epochs": 20,
  "epoch_metrics": [
    {
      "epoch": 1,
      "train_loss": 0.8195312742424011,
      "train_accuracy": 0.08446,
      "test_accuracy": 0.0836
    },
    {
      "epoch": 2,
      "train_loss": 0.8062163528442383,
      "train_accuracy": 0.08482,
      "test_accuracy": 0.0852
    },
    {
      "epoch": 3,
      "train_loss": 0.8037053998756408,
      "train_accuracy": 0.08724,
      "test_accuracy": 0.0836
    },
    {
      "epoch": 4,
      "train_loss": 0.8026957947540283,
      "train_accuracy": 0.08678,
      "test_accuracy": 0.0843
    },
    {
      "epoch": 5,
      "train_loss": 0.8021327345085144,
      "train_accuracy": 0.08552,
      "test_accuracy": 0.0859
    },
    {
      "epoch": 6,
      "train_loss": 0.8017679976463318,
      "train_accuracy": 0.085,
      "test_accuracy": 0.0859
    },
    {
      "epoch": 7,
      "train_loss": 0.8014352530670166,
      "train_accuracy": 0.08494,
      "test_accuracy": 0.0861
    },
    {
      "epoch": 8,
      "train_loss": 0.8012558493614197,
      "train_accuracy": 0.08692,
      "test_accuracy": 0.0844
    },
    {
      "epoch": 9,
      "train_loss": 0.8010444483757019,
      "train_accuracy": 0.08658,
      "test_accuracy": 0.0833
    },
    {
      "epoch": 10,
      "train_loss": 0.800995331993103,
      "train_accuracy": 0.08406,
      "test_accuracy": 0.0814
    },
    {
      "epoch": 11,
      "train_loss": 0.8008684412002564,
      "train_accuracy": 0.08572,
      "test_accuracy": 0.0809
    },
    {
      "epoch": 12,
      "train_loss": 0.8007626354026794,
      "train_accuracy": 0.0849,
      "test_accuracy": 0.0802
    },
    {
      "epoch": 13,
      "train_loss": 0.800724581375122,
      "train_accuracy": 0.08436,
      "test_accuracy": 0.0781
    },
    {
      "epoch": 14,
      "train_loss": 0.8006500570869446,
      "train_accuracy": 0.08302,
      "test_accuracy": 0.0826
    },
    {
      "epoch": 15,
      "train_loss": 0.8005710829353333,
      "train_accuracy": 0.08306,
      "test_accuracy": 0.0876
    },
    {
      "epoch": 16,
      "train_loss": 0.8005272212409973,
      "train_accuracy": 0.08108,
      "test_accuracy": 0.0861
    },
    {
      "epoch": 17,
      "train_loss": 0.800440772151947,
      "train_accuracy": 0.08502,
      "test_accuracy": 0.0842
    },
    {
      "epoch": 18,
      "train_loss": 0.8003684366035462,
      "train_accuracy": 0.08284,
      "test_accuracy": 0.0843
    },
    {
      "epoch": 19,
      "train_loss": 0.8003237868499756,
      "train_accuracy": 0.08578,
      "test_accuracy": 0.079
    },
    {
      "epoch": 20,
      "train_loss": 0.8002390389442444,
      "train_accuracy": 0.086,
      "test_accuracy": 0.0851
    }
  ],
  "neurobench": {}
}