{
  "name": "tp_fc_snn_nmnist_t1",
  "trainer": "tp",
  "model": "fc_snn",
  "dataset": "nmnist",
  "test_accuracy": 0.7347,
  "train_loss": 20.478770692124325,
  "elapsed_s": 283.9955506324768,
  "epochs": 20,
  "epoch_metrics": [
    {
      "epoch": 1,
      "train_loss": 56.057538079400345,
      "train_accuracy": 0.37545072115384615,
      "test_accuracy": 0.3619
    },
    {
      "epoch": 2,
      "train_loss": 45.839794468675926,
      "train_accuracy": 0.49550948183760685,
      "test_accuracy": 0.6197
    },
    {
      "epoch": 3,
      "train_loss": 51.00401183886406,
      "train_accuracy": 0.4900173611111111,
      "test_accuracy": 0.4064
    },
    {
      "epoch": 4,
      "train_loss": 45.60204506327963,
      "train_accuracy": 0.508346688034188,
      "test_accuracy": 0.5258
    },
    {
      "epoch": 5,
      "train_loss": 45.15454815595578,
      "train_accuracy": 0.5238047542735043,
      "test_accuracy": 0.5464
    },
    {
      "epoch": 6,
      "train_loss": 35.6945707451584,
      "train_accuracy": 0.5731503739316239,
      "test_accuracy": 0.513
    },
    {
      "epoch": 7,
      "train_loss": 44.01815298683623,
      "train_accuracy": 0.5517661591880342,
      "test_accuracy": 0.6253
    },
    {
      "epoch": 8,
      "train_loss": 30.675447879693447,
      "train_accuracy": 0.6326789529914529,
      "test_accuracy": 0.5347
    },
    {
      "epoch": 9,
      "train_loss": 31.42869723148835,
      "train_accuracy": 0.6441973824786325,
      "test_accuracy": 0.6464
    },
    {
      "epoch": 10,
      "train_loss": 29.633428373907368,
      "train_accuracy": 0.6761985844017094,
      "test_accuracy": 0.5299
    },
    {
      "epoch": 11,
      "train_loss": 26.276650241297535,
      "train_accuracy": 0.6977664262820513,
      "test_accuracy": 0.6564
    },
    {
      "epoch": 12,
      "train_loss": 24.85515878750728,
      "train_accuracy": 0.6988848824786325,
      "test_accuracy": 0.6871
    },
    {
      "epoch": 13,
      "train_loss": 23.124507720653828,
      "train_accuracy": 0.7151275373931624,
      "test_accuracy": 0.7278
    },
    {
      "epoch": 14,
      "train_loss": 22.94117544655107,
      "train_accuracy": 0.7316539797008547,
      "test_accuracy": 0.8159
    },
    {
      "epoch": 15,
      "train_loss": 22.57079574593112,
      "train_accuracy": 0.7377303685897436,
      "test_accuracy": 0.7114
    },
    {
      "epoch": 16,
      "train_loss": 21.14836174606258,
      "train_accuracy": 0.7395666399572649,
      "test_accuracy": 0.7462
    },
    {
      "epoch": 17,
      "train_loss": 21.930426200230915,
      "train_accuracy": 0.7442073985042735,
      "test_accuracy": 0.7024
    },
    {
      "epoch": 18,
      "train_loss": 21.26599190174005,
      "train_accuracy": 0.7545739850427351,
      "test_accuracy": 0.5397
    },
    {
      "epoch": 19,
      "train_loss": 22.287226216405884,
      "train_accuracy": 0.7530215010683761,
      "test_accuracy": 0.6309
    },
    {
      "epoch": 20,
      "train_loss": 20.478770692124325,
      "train_accuracy": 0.7607338408119658,
      "test_accuracy": 0.7347
    }
  ],
  "neurobench": {}
}