{
  "name": "bptt_conv_snn_mnist_t4",
  "trainer": "bptt",
  "model": "conv_snn",
  "dataset": "mnist",
  "test_accuracy": 0.9813,
  "train_loss": 1.4944031771977742,
  "elapsed_s": 83.09034991264343,
  "epochs": 20,
  "epoch_metrics": [
    {
      "epoch": 1,
      "train_loss": 1.963096405029297,
      "train_accuracy": 0.6507666666666667,
      "test_accuracy": 0.8653
    },
    {
      "epoch": 2,
      "train_loss": 1.6978755990346273,
      "train_accuracy": 0.8852166666666667,
      "test_accuracy": 0.9184
    },
    {
      "epoch": 3,
      "train_loss": 1.6454591562906902,
      "train_accuracy": 0.9213,
      "test_accuracy": 0.9377
    },
    {
      "epoch": 4,
      "train_loss": 1.599151698811849,
      "train_accuracy": 0.93775,
      "test_accuracy": 0.9487
    },
    {
      "epoch": 5,
      "train_loss": 1.5685335762023926,
      "train_accuracy": 0.9474666666666667,
      "test_accuracy": 0.9558
    },
    {
      "epoch": 6,
      "train_loss": 1.5500405103683472,
      "train_accuracy": 0.9541166666666666,
      "test_accuracy": 0.9614
    },
    {
      "epoch": 7,
      "train_loss": 1.537637464205424,
      "train_accuracy": 0.9598333333333333,
      "test_accuracy": 0.9649
    },
    {
      "epoch": 8,
      "train_loss": 1.5285090611139933,
      "train_accuracy": 0.9623666666666667,
      "test_accuracy": 0.9684
    },
    {
      "epoch": 9,
      "train_loss": 1.5219901186625162,
      "train_accuracy": 0.9654333333333334,
      "test_accuracy": 0.9705
    },
    {
      "epoch": 10,
      "train_loss": 1.5174636679967244,
      "train_accuracy": 0.9670166666666666,
      "test_accuracy": 0.9719
    },
    {
      "epoch": 11,
      "train_loss": 1.5130896158218383,
      "train_accuracy": 0.96955,
      "test_accuracy": 0.9725
    },
    {
      "epoch": 12,
      "train_loss": 1.509906933403015,
      "train_accuracy": 0.9712,
      "test_accuracy": 0.9738
    },
    {
      "epoch": 13,
      "train_loss": 1.5072549376169841,
      "train_accuracy": 0.9728333333333333,
      "test_accuracy": 0.9762
    },
    {
      "epoch": 14,
      "train_loss": 1.5047323831558228,
      "train_accuracy": 0.9738833333333333,
      "test_accuracy": 0.9766
    },
    {
      "epoch": 15,
      "train_loss": 1.5022712666829428,
      "train_accuracy": 0.9754666666666667,
      "test_accuracy": 0.9789
    },
    {
      "epoch": 16,
      "train_loss": 1.5007360569636028,
      "train_accuracy": 0.97595,
      "test_accuracy": 0.9793
    },
    {
      "epoch": 17,
      "train_loss": 1.4987735010782877,
      "train_accuracy": 0.9762166666666666,
      "test_accuracy": 0.9801
    },
    {
      "epoch": 18,
      "train_loss": 1.4971904123942057,
      "train_accuracy": 0.9782,
      "test_accuracy": 0.9798
    },
    {
      "epoch": 19,
      "train_loss": 1.4958162191390991,
      "train_accuracy": 0.9789833333333333,
      "test_accuracy": 0.9804
    },
    {
      "epoch": 20,
      "train_loss": 1.4944031771977742,
      "train_accuracy": 0.9790166666666666,
      "test_accuracy": 0.9813
    }
  ],
  "neurobench": {}
}