{
  "name": "decolle_fc_snn_fashionmnist_t7",
  "trainer": "decolle",
  "model": "fc_snn",
  "dataset": "fashionmnist",
  "test_accuracy": 0.7201,
  "train_loss": 0.6321365138689677,
  "elapsed_s": 68.82110118865967,
  "epochs": 20,
  "epoch_metrics": [
    {
      "epoch": 1,
      "train_loss": 1.0621349380175273,
      "train_accuracy": 0.35786666666666667,
      "test_accuracy": 0.5115
    },
    {
      "epoch": 2,
      "train_loss": 0.9126355274518331,
      "train_accuracy": 0.56335,
      "test_accuracy": 0.5944
    },
    {
      "epoch": 3,
      "train_loss": 0.8392766545295716,
      "train_accuracy": 0.6144833333333334,
      "test_accuracy": 0.625
    },
    {
      "epoch": 4,
      "train_loss": 0.7948279684384664,
      "train_accuracy": 0.6380666666666667,
      "test_accuracy": 0.6457
    },
    {
      "epoch": 5,
      "train_loss": 0.7646936685244242,
      "train_accuracy": 0.6527333333333334,
      "test_accuracy": 0.6565
    },
    {
      "epoch": 6,
      "train_loss": 0.7425583731969198,
      "train_accuracy": 0.66325,
      "test_accuracy": 0.6661
    },
    {
      "epoch": 7,
      "train_loss": 0.7252488167444865,
      "train_accuracy": 0.6724,
      "test_accuracy": 0.6744
    },
    {
      "epoch": 8,
      "train_loss": 0.7113439417521159,
      "train_accuracy": 0.6784,
      "test_accuracy": 0.6814
    },
    {
      "epoch": 9,
      "train_loss": 0.6996406594276429,
      "train_accuracy": 0.68585,
      "test_accuracy": 0.6873
    },
    {
      "epoch": 10,
      "train_loss": 0.6897817404429117,
      "train_accuracy": 0.6904333333333333,
      "test_accuracy": 0.6937
    },
    {
      "epoch": 11,
      "train_loss": 0.6811961721102396,
      "train_accuracy": 0.6956166666666667,
      "test_accuracy": 0.6981
    },
    {
      "epoch": 12,
      "train_loss": 0.6736010188738505,
      "train_accuracy": 0.6992666666666667,
      "test_accuracy": 0.7018
    },
    {
      "epoch": 13,
      "train_loss": 0.6669185288747151,
      "train_accuracy": 0.7041166666666666,
      "test_accuracy": 0.7047
    },
    {
      "epoch": 14,
      "train_loss": 0.6605742906252543,
      "train_accuracy": 0.7066833333333333,
      "test_accuracy": 0.7105
    },
    {
      "epoch": 15,
      "train_loss": 0.6550838996251425,
      "train_accuracy": 0.7090666666666666,
      "test_accuracy": 0.7111
    },
    {
      "epoch": 16,
      "train_loss": 0.6497168164253235,
      "train_accuracy": 0.7114,
      "test_accuracy": 0.7112
    },
    {
      "epoch": 17,
      "train_loss": 0.6448466311454772,
      "train_accuracy": 0.7132166666666667,
      "test_accuracy": 0.7135
    },
    {
      "epoch": 18,
      "train_loss": 0.6403411372184753,
      "train_accuracy": 0.71625,
      "test_accuracy": 0.7173
    },
    {
      "epoch": 19,
      "train_loss": 0.6361651241938273,
      "train_accuracy": 0.7167333333333333,
      "test_accuracy": 0.7187
    },
    {
      "epoch": 20,
      "train_loss": 0.6321365138689677,
      "train_accuracy": 0.7191166666666666,
      "test_accuracy": 0.7201
    }
  ],
  "neurobench": {}
}