{
  "name": "tp_r_snn_dvsgesture_t3",
  "trainer": "tp",
  "model": "r_snn",
  "dataset": "dvsgesture",
  "test_accuracy": 0.6553030303030303,
  "train_loss": 0.5965006500482559,
  "elapsed_s": 88.27002716064453,
  "epochs": 20,
  "epoch_metrics": [
    {
      "epoch": 1,
      "train_loss": 3.0248732566833496,
      "train_accuracy": 0.1640625,
      "test_accuracy": 0.29924242424242425
    },
    {
      "epoch": 2,
      "train_loss": 1.6937736868858337,
      "train_accuracy": 0.3740234375,
      "test_accuracy": 0.38257575757575757
    },
    {
      "epoch": 3,
      "train_loss": 1.347078949213028,
      "train_accuracy": 0.4716796875,
      "test_accuracy": 0.5416666666666666
    },
    {
      "epoch": 4,
      "train_loss": 1.1513236463069916,
      "train_accuracy": 0.5517578125,
      "test_accuracy": 0.5303030303030303
    },
    {
      "epoch": 5,
      "train_loss": 1.041153758764267,
      "train_accuracy": 0.6025390625,
      "test_accuracy": 0.5757575757575758
    },
    {
      "epoch": 6,
      "train_loss": 0.9660911560058594,
      "train_accuracy": 0.6044921875,
      "test_accuracy": 0.6136363636363636
    },
    {
      "epoch": 7,
      "train_loss": 0.9511689096689224,
      "train_accuracy": 0.6240234375,
      "test_accuracy": 0.6325757575757576
    },
    {
      "epoch": 8,
      "train_loss": 0.8818067461252213,
      "train_accuracy": 0.6318359375,
      "test_accuracy": 0.6401515151515151
    },
    {
      "epoch": 9,
      "train_loss": 0.8463101238012314,
      "train_accuracy": 0.6640625,
      "test_accuracy": 0.6136363636363636
    },
    {
      "epoch": 10,
      "train_loss": 0.8392349928617477,
      "train_accuracy": 0.662109375,
      "test_accuracy": 0.6401515151515151
    },
    {
      "epoch": 11,
      "train_loss": 0.7674577832221985,
      "train_accuracy": 0.67578125,
      "test_accuracy": 0.6325757575757576
    },
    {
      "epoch": 12,
      "train_loss": 0.7461233139038086,
      "train_accuracy": 0.68359375,
      "test_accuracy": 0.6553030303030303
    },
    {
      "epoch": 13,
      "train_loss": 0.7464501112699509,
      "train_accuracy": 0.6845703125,
      "test_accuracy": 0.6363636363636364
    },
    {
      "epoch": 14,
      "train_loss": 0.6964974105358124,
      "train_accuracy": 0.69921875,
      "test_accuracy": 0.6590909090909091
    },
    {
      "epoch": 15,
      "train_loss": 0.6908784508705139,
      "train_accuracy": 0.703125,
      "test_accuracy": 0.6515151515151515
    },
    {
      "epoch": 16,
      "train_loss": 0.6667340993881226,
      "train_accuracy": 0.7158203125,
      "test_accuracy": 0.6704545454545454
    },
    {
      "epoch": 17,
      "train_loss": 0.6470589190721512,
      "train_accuracy": 0.73046875,
      "test_accuracy": 0.6325757575757576
    },
    {
      "epoch": 18,
      "train_loss": 0.6092774718999863,
      "train_accuracy": 0.73828125,
      "test_accuracy": 0.6325757575757576
    },
    {
      "epoch": 19,
      "train_loss": 0.6211105734109879,
      "train_accuracy": 0.7392578125,
      "test_accuracy": 0.6439393939393939
    },
    {
      "epoch": 20,
      "train_loss": 0.5965006500482559,
      "train_accuracy": 0.75,
      "test_accuracy": 0.6553030303030303
    }
  ],
  "neurobench": {}
}