{
  "name": "osttp_r_snn_cifar10_t3",
  "trainer": "osttp",
  "model": "r_snn",
  "dataset": "cifar10",
  "test_accuracy": 0.1,
  "train_loss": 6051.55988609375,
  "elapsed_s": 2635.1746401786804,
  "epochs": 20,
  "epoch_metrics": [
    {
      "epoch": 1,
      "train_loss": 946.4605550396728,
      "train_accuracy": 0.09914,
      "test_accuracy": 0.1
    },
    {
      "epoch": 2,
      "train_loss": 1042.5385051171875,
      "train_accuracy": 0.1,
      "test_accuracy": 0.1
    },
    {
      "epoch": 3,
      "train_loss": 1042.4332380859375,
      "train_accuracy": 0.1,
      "test_accuracy": 0.1
    },
    {
      "epoch": 4,
      "train_loss": 1041.226532421875,
      "train_accuracy": 0.1,
      "test_accuracy": 0.1
    },
    {
      "epoch": 5,
      "train_loss": 1039.8372284765626,
      "train_accuracy": 0.1,
      "test_accuracy": 0.1
    },
    {
      "epoch": 6,
      "train_loss": 1036.43860375,
      "train_accuracy": 0.1,
      "test_accuracy": 0.1
    },
    {
      "epoch": 7,
      "train_loss": 1149.138720859375,
      "train_accuracy": 0.09972,
      "test_accuracy": 0.1
    },
    {
      "epoch": 8,
      "train_loss": 2889.858864375,
      "train_accuracy": 0.1,
      "test_accuracy": 0.1
    },
    {
      "epoch": 9,
      "train_loss": 2896.57211046875,
      "train_accuracy": 0.1,
      "test_accuracy": 0.1
    },
    {
      "epoch": 10,
      "train_loss": 2901.5874784375,
      "train_accuracy": 0.1,
      "test_accuracy": 0.1
    },
    {
      "epoch": 11,
      "train_loss": 2908.4535740625,
      "train_accuracy": 0.1,
      "test_accuracy": 0.1
    },
    {
      "epoch": 12,
      "train_loss": 2907.17994875,
      "train_accuracy": 0.1,
      "test_accuracy": 0.1
    },
    {
      "epoch": 13,
      "train_loss": 2906.607454375,
      "train_accuracy": 0.09994,
      "test_accuracy": 0.1
    },
    {
      "epoch": 14,
      "train_loss": 5871.6509465625,
      "train_accuracy": 0.1,
      "test_accuracy": 0.1
    },
    {
      "epoch": 15,
      "train_loss": 6129.90768171875,
      "train_accuracy": 0.1,
      "test_accuracy": 0.1
    },
    {
      "epoch": 16,
      "train_loss": 6093.143289375,
      "train_accuracy": 0.1,
      "test_accuracy": 0.1
    },
    {
      "epoch": 17,
      "train_loss": 6033.951899375,
      "train_accuracy": 0.1,
      "test_accuracy": 0.1
    },
    {
      "epoch": 18,
      "train_loss": 6036.930626875,
      "train_accuracy": 0.1,
      "test_accuracy": 0.1
    },
    {
      "epoch": 19,
      "train_loss": 6054.37150625,
      "train_accuracy": 0.1,
      "test_accuracy": 0.1
    },
    {
      "epoch": 20,
      "train_loss": 6051.55988609375,
      "train_accuracy": 0.1,
      "test_accuracy": 0.1
    }
  ],
  "neurobench": {}
}