{
  "name": "ottt_fc_snn_cifar10_t3",
  "trainer": "ottt",
  "model": "fc_snn",
  "dataset": "cifar10",
  "test_accuracy": 0.3205,
  "train_loss": 1.5112502299118042,
  "elapsed_s": 106.65440654754639,
  "epochs": 20,
  "epoch_metrics": [
    {
      "epoch": 1,
      "train_loss": 1.9487123519134522,
      "train_accuracy": 0.29464,
      "test_accuracy": 0.3184
    },
    {
      "epoch": 2,
      "train_loss": 1.81031914352417,
      "train_accuracy": 0.31888,
      "test_accuracy": 0.3378
    },
    {
      "epoch": 3,
      "train_loss": 1.7517128721237183,
      "train_accuracy": 0.32136,
      "test_accuracy": 0.337
    },
    {
      "epoch": 4,
      "train_loss": 1.7086089336395263,
      "train_accuracy": 0.32276,
      "test_accuracy": 0.3407
    },
    {
      "epoch": 5,
      "train_loss": 1.6802991174697877,
      "train_accuracy": 0.32574,
      "test_accuracy": 0.3019
    },
    {
      "epoch": 6,
      "train_loss": 1.658443291168213,
      "train_accuracy": 0.32638,
      "test_accuracy": 0.3328
    },
    {
      "epoch": 7,
      "train_loss": 1.6349082934951782,
      "train_accuracy": 0.32348,
      "test_accuracy": 0.3377
    },
    {
      "epoch": 8,
      "train_loss": 1.6157106703948974,
      "train_accuracy": 0.31974,
      "test_accuracy": 0.328
    },
    {
      "epoch": 9,
      "train_loss": 1.608722383041382,
      "train_accuracy": 0.31678,
      "test_accuracy": 0.3193
    },
    {
      "epoch": 10,
      "train_loss": 1.5984181748962403,
      "train_accuracy": 0.31452,
      "test_accuracy": 0.3166
    },
    {
      "epoch": 11,
      "train_loss": 1.5829337753295898,
      "train_accuracy": 0.31342,
      "test_accuracy": 0.3198
    },
    {
      "epoch": 12,
      "train_loss": 1.5737306875228882,
      "train_accuracy": 0.31554,
      "test_accuracy": 0.3189
    },
    {
      "epoch": 13,
      "train_loss": 1.5614508227539063,
      "train_accuracy": 0.31132,
      "test_accuracy": 0.3062
    },
    {
      "epoch": 14,
      "train_loss": 1.5549062619781495,
      "train_accuracy": 0.31366,
      "test_accuracy": 0.3022
    },
    {
      "epoch": 15,
      "train_loss": 1.5492419164657594,
      "train_accuracy": 0.31316,
      "test_accuracy": 0.3169
    },
    {
      "epoch": 16,
      "train_loss": 1.5399903066635132,
      "train_accuracy": 0.30982,
      "test_accuracy": 0.3086
    },
    {
      "epoch": 17,
      "train_loss": 1.5267532387924194,
      "train_accuracy": 0.31082,
      "test_accuracy": 0.3012
    },
    {
      "epoch": 18,
      "train_loss": 1.5226828820419311,
      "train_accuracy": 0.30914,
      "test_accuracy": 0.2909
    },
    {
      "epoch": 19,
      "train_loss": 1.5126896312332154,
      "train_accuracy": 0.30726,
      "test_accuracy": 0.2917
    },
    {
      "epoch": 20,
      "train_loss": 1.5112502299118042,
      "train_accuracy": 0.31346,
      "test_accuracy": 0.3205
    }
  ],
  "neurobench": {}
}