{
  "name": "decolle_conv_snn_dvscifar10_t3",
  "trainer": "decolle",
  "model": "conv_snn",
  "dataset": "dvscifar10",
  "test_accuracy": 0.311,
  "train_loss": 0.7681064233183861,
  "elapsed_s": 857.4953894615173,
  "epochs": 20,
  "epoch_metrics": [
    {
      "epoch": 1,
      "train_loss": 3.7000821041209355,
      "train_accuracy": 0.23805803571428572,
      "test_accuracy": 0.201
    },
    {
      "epoch": 2,
      "train_loss": 4.397732721056257,
      "train_accuracy": 0.28805803571428573,
      "test_accuracy": 0.172
    },
    {
      "epoch": 3,
      "train_loss": 3.6819734939507076,
      "train_accuracy": 0.35167410714285713,
      "test_accuracy": 0.211
    },
    {
      "epoch": 4,
      "train_loss": 4.4983529712472645,
      "train_accuracy": 0.32912946428571427,
      "test_accuracy": 0.156
    },
    {
      "epoch": 5,
      "train_loss": 4.2738473551613945,
      "train_accuracy": 0.35948660714285713,
      "test_accuracy": 0.126
    },
    {
      "epoch": 6,
      "train_loss": 3.9865828284195493,
      "train_accuracy": 0.39017857142857143,
      "test_accuracy": 0.124
    },
    {
      "epoch": 7,
      "train_loss": 3.294855032648359,
      "train_accuracy": 0.44497767857142856,
      "test_accuracy": 0.183
    },
    {
      "epoch": 8,
      "train_loss": 4.423609640768596,
      "train_accuracy": 0.4160714285714286,
      "test_accuracy": 0.166
    },
    {
      "epoch": 9,
      "train_loss": 4.737752059527806,
      "train_accuracy": 0.4160714285714286,
      "test_accuracy": 0.169
    },
    {
      "epoch": 10,
      "train_loss": 2.5051873675414496,
      "train_accuracy": 0.5146205357142857,
      "test_accuracy": 0.238
    },
    {
      "epoch": 11,
      "train_loss": 4.314521242039544,
      "train_accuracy": 0.4310267857142857,
      "test_accuracy": 0.158
    },
    {
      "epoch": 12,
      "train_loss": 3.2694028522287097,
      "train_accuracy": 0.49899553571428573,
      "test_accuracy": 0.241
    },
    {
      "epoch": 13,
      "train_loss": 2.2332826201404843,
      "train_accuracy": 0.5672991071428571,
      "test_accuracy": 0.242
    },
    {
      "epoch": 14,
      "train_loss": 2.1725489122526986,
      "train_accuracy": 0.5766741071428572,
      "test_accuracy": 0.26
    },
    {
      "epoch": 15,
      "train_loss": 4.365311178990773,
      "train_accuracy": 0.4753348214285714,
      "test_accuracy": 0.288
    },
    {
      "epoch": 16,
      "train_loss": 0.9928715356758663,
      "train_accuracy": 0.6736607142857143,
      "test_accuracy": 0.269
    },
    {
      "epoch": 17,
      "train_loss": 1.443156132740634,
      "train_accuracy": 0.6670758928571429,
      "test_accuracy": 0.178
    },
    {
      "epoch": 18,
      "train_loss": 2.037031825312546,
      "train_accuracy": 0.6239955357142857,
      "test_accuracy": 0.291
    },
    {
      "epoch": 19,
      "train_loss": 3.0533873858196396,
      "train_accuracy": 0.5689732142857142,
      "test_accuracy": 0.311
    },
    {
      "epoch": 20,
      "train_loss": 0.7681064233183861,
      "train_accuracy": 0.7388392857142857,
      "test_accuracy": 0.311
    }
  ],
  "neurobench": {}
}